CHANGELOG.txt
LICENCE.txt
MANIFEST.in
README.txt
setup.py
test.py
AhmedHossam/__init__.py
AhmedHossam/main.py
ahmedHossam.egg-info/PKG-INFO
ahmedHossam.egg-info/SOURCES.txt
ahmedHossam.egg-info/dependency_links.txt
ahmedHossam.egg-info/top_level.txt